mypkg/__init__.py
mypkg/imgkernel.py
mypkg/kernels.py
mypkg1xz/__init__.py
mypkg1xz/imgkernel.py
mypkg1xz/kernels.py
mypkg1xz-0.0.1.dist-info/LICENSE
mypkg1xz-0.0.1.dist-info/METADATA
mypkg1xz-0.0.1.dist-info/WHEEL
mypkg1xz-0.0.1.dist-info/top_level.txt
mypkg1xz-0.0.1.dist-info/RECORD
